napari_sdeconv/__init__.py
napari_sdeconv/_dict_widget.py
napari_sdeconv/_dict_worker.py
napari_sdeconv/_framework.py
napari_sdeconv/_sample_data.py
napari_sdeconv/_sdeconv_widget.py
napari_sdeconv/_spsf_widget.py
napari_sdeconv/napari.yaml
napari_sdeconv/_tests/__init__.py
napari_sdeconv/_tests/test_sample_data.py
napari_sdeconv/_tests/test_widget.py
napari_sdeconv-1.0.1.dist-info/LICENSE
napari_sdeconv-1.0.1.dist-info/METADATA
napari_sdeconv-1.0.1.dist-info/WHEEL
napari_sdeconv-1.0.1.dist-info/entry_points.txt
napari_sdeconv-1.0.1.dist-info/top_level.txt
napari_sdeconv-1.0.1.dist-info/RECORD
