Metadata-Version: 2.1
Name: napari-sdeconv
Version: 1.0.1
Summary: 2D and 3D deconvolution
Home-page: https://github.com/sylvainprigent/napari-sdeconv
Author: Sylvain Prigent
Author-email: meriadec.prigent@gmail.com
License: BSD-3-Clause
Project-URL: Bug Tracker, https://github.com/sylvainprigent/napari-sdeconv/issues
Project-URL: Documentation, https://github.com/sylvainprigent/napari-sdeconv#README.md
Project-URL: Source Code, https://github.com/sylvainprigent/napari-sdeconv
Project-URL: User Support, https://github.com/sylvainprigent/napari-sdeconv/issues
Classifier: Development Status :: 2 - Pre-Alpha
Classifier: Framework :: napari
Classifier: Intended Audience :: Developers
Classifier: License :: OSI Approved :: BSD License
Classifier: Operating System :: OS Independent
Classifier: Programming Language :: Python
Classifier: Programming Language :: Python :: 3
Classifier: Programming Language :: Python :: 3 :: Only
Classifier: Programming Language :: Python :: 3.8
Classifier: Programming Language :: Python :: 3.9
Classifier: Programming Language :: Python :: 3.10
Classifier: Topic :: Software Development :: Testing
Requires-Python: >=3.8
License-File: LICENSE
Requires-Dist: numpy
Requires-Dist: magicgui
Requires-Dist: qtpy
Requires-Dist: sdeconv (>=1.0.1)
Provides-Extra: testing
Requires-Dist: tox ; extra == 'testing'
Requires-Dist: pytest ; extra == 'testing'
Requires-Dist: pytest-cov ; extra == 'testing'
Requires-Dist: pytest-qt ; extra == 'testing'
Requires-Dist: napari ; extra == 'testing'
Requires-Dist: pyqt5 ; extra == 'testing'
Requires-Dist: sdeconv (>=1.0.1) ; extra == 'testing'
